{"cameraMode":{"drawMode":0,"name":"Shaded","section":"Shading Mode"},"sceneLighting":true,"audioPlay":false,"sceneViewState":{"showFog":true,"showMaterialUpdate":false,"showSkybox":true,"showFlares":true,"showImageEffects":true,"showParticleSystems":true,"showVisualEffectGraphs":true,"m_FxEnabled":true},"in2DMode":false,"pivot":{"x":458.1576232910156,"y":-465.14013671875,"z":512.9556884765625},"rotation":{"x":-0.2763257324695587,"y":-0.33900171518325808,"z":0.1048089787364006,"w":-0.8932173252105713},"size":548.9517822265625,"orthographic":false}